[
    {
        "idEType":"etype_Hanomy",
        "nameEType":"Hanomy",
        "UrlImageEType":"https://firebasestorage.googleapis.com/v0/b/chillkra-dc0e4.appspot.com/o/ImageEtypes%2FGroup%201225%402x.png?alt=media&token=512113d0-b411-4588-9cb0-913d8e13b81c"
    },
    
    {
        "idEType":"etype_Calm",
        "nameEType":"Calm",
        "UrlImageEType":"https://firebasestorage.googleapis.com/v0/b/chillkra-dc0e4.appspot.com/o/ImageEtypes%2FGroup%201227%402x.png?alt=media&token=c4518058-92de-4484-9c8d-3e72bbe55505"
    },
    
    {
        "idEType":"etype_Relax",
        "nameEType":"Relax",
        "UrlImageEType":"https://firebasestorage.googleapis.com/v0/b/chillkra-dc0e4.appspot.com/o/ImageEtypes%2FGroup%201229%402x.png?alt=media&token=3a7e34c6-5486-4596-918a-2f74e2b9015b"
    },
    
    {
        "idEType":"etype_Lost",
        "nameEType":"Lost",
        "UrlImageEType":"https://firebasestorage.googleapis.com/v0/b/chillkra-dc0e4.appspot.com/o/ImageEtypes%2FGroup%201231%402x.png?alt=media&token=e22ac1c0-01f9-42ad-9c8d-c518917a7e68"
    },
]

